travelersApi/__init__.py
travelersApi/lowApi.py
travelersApi/noise.py
travelersApi/travelerApi.py
travelersApi/types.py
travelersApi/world.py
thetravelers.online_Api-1.3.1.dist-info/METADATA
thetravelers.online_Api-1.3.1.dist-info/WHEEL
thetravelers.online_Api-1.3.1.dist-info/top_level.txt
thetravelers.online_Api-1.3.1.dist-info/RECORD
