Metadata-Version: 2.1
Name: thetravelers.online-Api
Version: 1.3.1
Summary: Python API for thetravelers.online
Home-page: https://github.com/LightningWB/thetravelers.online-API
Author: LightningWB
License: MIT
Platform: UNKNOWN
Requires-Dist: selenium
